gbapi/__init__.py
gbapi/client.py
gbapi/api/__init__.py
gbapi/api/author.py
gbapi/api/base_submission.py
gbapi/api/game.py
gbapi/api/stats.py
gbapi/api/structured_data.py
gbapi/api/url_factory.py
gbapi/structures/__init__.py
gbapi/structures/all.py
gbapi/structures/blog.py
gbapi/structures/castaway.py
gbapi/structures/concept.py
gbapi/structures/effect.py
gbapi/structures/gamefile.py
gbapi/structures/gui.py
gbapi/structures/init.py
gbapi/structures/map.py
gbapi/structures/prefab.py
gbapi/structures/project.py
gbapi/structures/question.py
gbapi/structures/request.py
gbapi/structures/script.py
gbapi/structures/skin.py
gbapi/structures/sound.py
gbapi/structures/spray.py
gbapi/structures/texture.py
gbapi/structures/thread.py
gbapi/structures/tool.py
gbapi/structures/tutorial.py
gbapi/structures/ware.py
gbapi/structures/wip.py
gbapi/structures/sub/__init__.py
gbapi/structures/sub/wip.py
gbapi-0.2.0.dist-info/LICENSE
gbapi-0.2.0.dist-info/METADATA
gbapi-0.2.0.dist-info/WHEEL
gbapi-0.2.0.dist-info/top_level.txt
gbapi-0.2.0.dist-info/RECORD
