Metadata-Version: 2.1
Name: gbapi
Version: 0.2.0
Summary: qeaml's wrapper for GameBanana's API
Home-page: https://github.com/QeaML/gbapi
Author: qeaml
Author-email: qeaml@wp.pl
License: MIT
Platform: UNKNOWN
Classifier: Programming Language :: Python :: 3
Classifier: License :: OSI Approved :: MIT License
Classifier: Operating System :: OS Independent
Requires-Python: >=3.6
Requires-Dist: aiohttp
